README.md
hi_tea.py
setup.py
dcrypr1.egg-info/PKG-INFO
dcrypr1.egg-info/SOURCES.txt
dcrypr1.egg-info/dependency_links.txt
dcrypr1.egg-info/entry_points.txt
dcrypr1.egg-info/requires.txt
dcrypr1.egg-info/top_level.txt